efficalc/__init__.py
efficalc/calculation_runner.py
efficalc/constants.py
efficalc/generate_html.py
efficalc/report_builder.py
efficalc/unit_conversions.py
efficalc/base_definitions/__init__.py
efficalc/base_definitions/assumption.py
efficalc/base_definitions/calculation.py
efficalc/base_definitions/comparison.py
efficalc/base_definitions/comparison_statement.py
efficalc/base_definitions/figure.py
efficalc/base_definitions/heading.py
efficalc/base_definitions/input.py
efficalc/base_definitions/shared.py
efficalc/base_definitions/symbolic.py
efficalc/base_definitions/table.py
efficalc/base_definitions/text_block.py
efficalc/base_definitions/title.py
efficalc/canvas/__init__.py
efficalc/canvas/canvas.py
efficalc/canvas/canvas_elements.py
efficalc/sections/__init__.py
efficalc/sections/aisc_angle.py
efficalc/sections/aisc_channel.py
efficalc/sections/aisc_circular.py
efficalc/sections/aisc_double_angle.py
efficalc/sections/aisc_rectangular.py
efficalc/sections/aisc_tee.py
efficalc/sections/aisc_wide_flange.py
efficalc/sections/alum_angle.py
efficalc/sections/alum_channel.py
efficalc/sections/alum_circular.py
efficalc/sections/alum_rectangular.py
efficalc/sections/alum_wide_flange.py
efficalc/sections/section_properties.db
efficalc/sections/section_query.py
efficalc-1.2.7.dist-info/LICENSE
efficalc-1.2.7.dist-info/METADATA
efficalc-1.2.7.dist-info/WHEEL
efficalc-1.2.7.dist-info/top_level.txt
efficalc-1.2.7.dist-info/RECORD
