Metadata-Version: 2.1
Name: efficalc
Version: 1.2.7
Summary: Feature-rich open source library for building well-formatted and extensible engineering calculations.
Author-email: Andrew Young <youandvern@gmail.com>
Project-URL: Homepage, https://github.com/youandvern/efficalc
Project-URL: Documentation, https://youandvern.github.io/efficalc
Project-URL: Issues, https://github.com/youandvern/efficalc/issues
Classifier: Programming Language :: Python :: 3
Classifier: License :: OSI Approved :: MIT License
Classifier: Operating System :: OS Independent
Requires-Python: >=3.10
License-File: LICENSE
Requires-Dist: latexexpr_efficalc>=0.5.3
Requires-Dist: pylatexenc>=2.10
Requires-Dist: pytest>=8.0.2
